jict_dict/__init__.py
jict_dict/jict.py
jict_dict-1.0.0.dist-info/METADATA
jict_dict-1.0.0.dist-info/WHEEL
jict_dict-1.0.0.dist-info/top_level.txt
jict_dict-1.0.0.dist-info/RECORD
