Metadata-Version: 2.4
Name: jict-dict
Version: 1.0.0
Summary: JICT. a powerfull bidirectional dict
Author: eljeiforeal
License: MIT
Requires-Python: >=3.6
